setup.py
mload/__init__.py
mload.egg-info/PKG-INFO
mload.egg-info/SOURCES.txt
mload.egg-info/dependency_links.txt
mload.egg-info/not-zip-safe
mload.egg-info/top_level.txt