Metadata-Version: 1.0
Name: mload
Version: 0.1
Summary: Machine Learning for Outlier and Anomaly Detection.
Home-page: http://github.com/chaosimpler/aodetect
Author: Wang Chao
Author-email: chaosimpler@gmail.com
License: MIT
Platform: UNKNOWN
